wclip-0.1.2.dist-info/licenses/LICENSE
webclipboard/__init__.py
webclipboard/__main__.py
webclipboard/server.py
wclip-0.1.2.dist-info/METADATA
wclip-0.1.2.dist-info/WHEEL
wclip-0.1.2.dist-info/entry_points.txt
wclip-0.1.2.dist-info/top_level.txt
wclip-0.1.2.dist-info/RECORD
