Metadata-Version: 2.4
Name: wclip
Version: 0.1.2
Summary: A web-based clipboard sharing server
Author: Webclipboard Contributors
License: MIT
Project-URL: Homepage, https://github.com/ifabos/webclipboard
Project-URL: Bug Tracker, https://github.com/ifabos/webclipboard/issues
Keywords: clipboard,web,server,utility
Classifier: License :: OSI Approved :: MIT License
Classifier: Programming Language :: Python :: 3
Classifier: Programming Language :: Python :: 3.6
Classifier: Programming Language :: Python :: 3.7
Classifier: Programming Language :: Python :: 3.8
Classifier: Programming Language :: Python :: 3.9
Classifier: Programming Language :: Python :: 3.10
Classifier: Programming Language :: Python :: 3.11
Classifier: Topic :: Utilities
Requires-Python: >=3.6
License-File: LICENSE
Requires-Dist: pyperclip>=1.8.0
Dynamic: license-file
Dynamic: requires-python
